flastic-1.0.1.data/scripts/app.py
flastic-1.0.1.data/scripts/flastic
run/__init__.py
flastic-1.0.1.dist-info/METADATA
flastic-1.0.1.dist-info/WHEEL
flastic-1.0.1.dist-info/top_level.txt
flastic-1.0.1.dist-info/RECORD
