Metadata-Version: 2.1
Name: flastic
Version: 1.0.1
Summary: development static server
Home-page: UNKNOWN
Author: raravel
Author-email: youn@tree-some.dev
License: MIT
Platform: UNKNOWN
